{"deputadoId":132504,"eixos":{"id":132504,"nome":"Enio Verri","foto":"https://www.camara.leg.br/internet/deputado/bandep/132504.jpg","partido":"PT","uf":"PR","totalProposicoes":27,"eixoPredominante":"saude","eixos":[{"eixo":"saude","total":2},{"eixo":"economico","total":2},{"eixo":"social","total":2}],"termos":[{"termo":"Sessao","frequencia":14,"peso":5},{"termo":"Solene","frequencia":13,"peso":5},{"termo":"Realizacao","frequencia":11,"peso":4},{"termo":"Frente","frequencia":10,"peso":4},{"termo":"Registro","frequencia":9,"peso":4},{"termo":"Defesa","frequencia":7,"peso":3},{"termo":"Mista","frequencia":7,"peso":3},{"termo":"Deputados","frequencia":5,"peso":2},{"termo":"Homenagens e Datas Comemorativas","frequencia":4,"peso":2},{"termo":"Aniversario","frequencia":3,"peso":2},{"termo":"Comemoracao","frequencia":3,"peso":2},{"termo":"Criação","frequencia":3,"peso":2},{"termo":"Abril","frequencia":2,"peso":1},{"termo":"Advocacia","frequencia":2,"peso":1}]},"custoBeneficio":{"deputadoId":132504,"nome":"Enio Verri","partido":"S.PART.","uf":"—","urlFoto":"https://www.camara.leg.br/internet/deputado/bandep/132504.jpg","gastoTotal":70442.84,"totalProposicoes":27,"scoreBeneficio":27,"scoreCustoBeneficio":38.3289,"presencaPlenario":{"totalSessoes":0,"presencas":0,"ausenciasJustificadas":0,"ausenciasNaoJustificadas":0,"percentualPresenca":0},"formula":{"proposicao":1,"presencaPlenario":1,"escala":100000},"baseCustoReduzida":true,"posicaoGeral":314,"faixa":"Regular"},"fornecedores":{"deputadoId":132504,"totalGasto":70442.84,"totalFornecedores":10,"fornecedores":[{"fornecedor":"FERNANDO CUNHA NEVES","cnpjCpf":"487.897.330/0018-3","totalGasto":36000,"transacoes":1,"ticketMedio":36000,"percentual":51.11,"deputadosMesmoPartido":1,"alertaConcentracao":true,"alertaMesmoPartido":false},{"fornecedor":"A SANT ANA ANDRADE SCHMIDT - MARKETING E TREINAMENTO ME","cnpjCpf":"284.730.770/0010-6","totalGasto":15000,"transacoes":1,"ticketMedio":15000,"percentual":21.29,"deputadosMesmoPartido":1,"alertaConcentracao":false,"alertaMesmoPartido":false},{"fornecedor":"TAM","cnpjCpf":null,"totalGasto":5966.85,"transacoes":9,"ticketMedio":662.98,"percentual":8.47,"deputadosMesmoPartido":0,"alertaConcentracao":false,"alertaMesmoPartido":false},{"fornecedor":"MARFAM ASSESSORIA COMERCIAL LTDA","cnpjCpf":"060.573.690/0011-7","totalGasto":3928.54,"transacoes":1,"ticketMedio":3928.54,"percentual":5.58,"deputadosMesmoPartido":1,"alertaConcentracao":false,"alertaMesmoPartido":false},{"fornecedor":"AZUL","cnpjCpf":null,"totalGasto":3372.68,"transacoes":5,"ticketMedio":674.54,"percentual":4.79,"deputadosMesmoPartido":0,"alertaConcentracao":false,"alertaMesmoPartido":false},{"fornecedor":"GOL","cnpjCpf":null,"totalGasto":2853.3,"transacoes":2,"ticketMedio":1426.65,"percentual":4.05,"deputadosMesmoPartido":0,"alertaConcentracao":false,"alertaMesmoPartido":false},{"fornecedor":"TAM LINHAS AEREAS S/A.","cnpjCpf":"020.128.620/0016-0","totalGasto":1575.71,"transacoes":1,"ticketMedio":1575.71,"percentual":2.24,"deputadosMesmoPartido":36,"alertaConcentracao":false,"alertaMesmoPartido":true},{"fornecedor":"Gol Linhas Aereas Inteligentes","cnpjCpf":"061.642.530/0018-7","totalGasto":1362.85,"transacoes":1,"ticketMedio":1362.85,"percentual":1.93,"deputadosMesmoPartido":2,"alertaConcentracao":false,"alertaMesmoPartido":true}]},"categoriasDespesa":{"deputadoId":132504,"totalGasto":70442.84,"totalCategorias":5,"categorias":[{"categoria":"DIVULGAÇÃO DA ATIVIDADE PARLAMENTAR.","totalGasto":51000,"quantidadeDespesas":2,"percentual":72.4},{"categoria":"PASSAGEM AÉREA - SIGEPA","totalGasto":12192.83,"quantidadeDespesas":16,"percentual":17.31},{"categoria":"MANUTENÇÃO DE ESCRITÓRIO DE APOIO À ATIVIDADE PARLAMENTAR","totalGasto":3928.54,"quantidadeDespesas":1,"percentual":5.58},{"categoria":"PASSAGEM AÉREA - REEMBOLSO","totalGasto":2938.56,"quantidadeDespesas":2,"percentual":4.17},{"categoria":"TELEFONIA","totalGasto":382.91,"quantidadeDespesas":4,"percentual":0.54}]}}
