{"deputadoId":204358,"eixos":{"id":204358,"nome":"Beto Pereira","foto":"https://www.camara.leg.br/internet/deputado/bandep/204358.jpg","partido":"REPUBLIC","uf":"MS","totalProposicoes":200,"eixoPredominante":"economico","eixos":[{"eixo":"economico","total":99},{"eixo":"social","total":74},{"eixo":"seguranca","total":66}],"termos":[{"termo":"Frente","frequencia":76,"peso":5},{"termo":"Administração Pública","frequencia":60,"peso":4},{"termo":"Registro","frequencia":52,"peso":4},{"termo":"Criação","frequencia":50,"peso":4},{"termo":"Mista","frequencia":46,"peso":4},{"termo":"Direitos Humanos e Minorias","frequencia":44,"peso":3},{"termo":"Finanças Públicas e Orçamento","frequencia":44,"peso":3},{"termo":"Constituicao Federal 1988","frequencia":40,"peso":3},{"termo":"Processo Legislativo e Atuacao","frequencia":40,"peso":3},{"termo":"Saúde","frequencia":30,"peso":2},{"termo":"Defesa","frequencia":28,"peso":2},{"termo":"Defesa e Segurança","frequencia":28,"peso":2},{"termo":"Trabalho e Emprego","frequencia":28,"peso":2},{"termo":"Redacao","frequencia":22,"peso":2}]},"custoBeneficio":{"deputadoId":204358,"nome":"Beto Pereira","partido":"REPUBLICANOS","uf":"MS","urlFoto":"https://www.camara.leg.br/internet/deputado/bandep/204358.jpg","gastoTotal":1817658.75,"totalProposicoes":251,"scoreBeneficio":343.56,"scoreCustoBeneficio":18.9012,"presencaPlenario":{"totalSessoes":390,"presencas":361,"ausenciasJustificadas":24,"ausenciasNaoJustificadas":5,"percentualPresenca":92.56},"formula":{"proposicao":1,"presencaPlenario":1,"escala":100000},"baseCustoReduzida":false,"posicaoGeral":516,"faixa":"Baixo CxB"},"fornecedores":{"deputadoId":204358,"totalGasto":1817658.75,"totalFornecedores":59,"fornecedores":[{"fornecedor":"TRIART COMUNICAÇÃO E MARKETING LTDA","cnpjCpf":"319.096.840/0017-2","totalGasto":535000,"transacoes":30,"ticketMedio":17833.33,"percentual":29.43,"deputadosMesmoPartido":1,"alertaConcentracao":false,"alertaMesmoPartido":false},{"fornecedor":"ANCELMO E PAULINO LTDA","cnpjCpf":"049.904.400/0019-4","totalGasto":223857.44,"transacoes":57,"ticketMedio":3927.32,"percentual":12.32,"deputadosMesmoPartido":1,"alertaConcentracao":false,"alertaMesmoPartido":false},{"fornecedor":"RENTAL LOCADORA DE BENS E VEICULOS LTDA","cnpjCpf":"368.011.990/0010-2","totalGasto":216300,"transacoes":39,"ticketMedio":5546.15,"percentual":11.9,"deputadosMesmoPartido":1,"alertaConcentracao":false,"alertaMesmoPartido":false},{"fornecedor":"TAM","cnpjCpf":null,"totalGasto":157988.39,"transacoes":206,"ticketMedio":766.93,"percentual":8.69,"deputadosMesmoPartido":0,"alertaConcentracao":false,"alertaMesmoPartido":false},{"fornecedor":"RENTAL LOCADORA DE BENS E VEICULOS LTDA EPP","cnpjCpf":"368.011.990/0010-2","totalGasto":99100,"transacoes":21,"ticketMedio":4719.05,"percentual":5.45,"deputadosMesmoPartido":1,"alertaConcentracao":false,"alertaMesmoPartido":false},{"fornecedor":"KARINE BEZERRA VIANA ME","cnpjCpf":"194.705.480/0012-3","totalGasto":82500,"transacoes":15,"ticketMedio":5500,"percentual":4.54,"deputadosMesmoPartido":1,"alertaConcentracao":false,"alertaMesmoPartido":false},{"fornecedor":"IMAGETECH TECNOLOGIA EM INFORMATICA LTDA","cnpjCpf":"055.836.800/0013-7","totalGasto":74480,"transacoes":28,"ticketMedio":2660,"percentual":4.1,"deputadosMesmoPartido":1,"alertaConcentracao":false,"alertaMesmoPartido":false},{"fornecedor":"TAVARES & PENEDRO GRAFICA E EDITORA LTDA","cnpjCpf":"070.701.720/0018-0","totalGasto":55500,"transacoes":1,"ticketMedio":55500,"percentual":3.05,"deputadosMesmoPartido":1,"alertaConcentracao":false,"alertaMesmoPartido":false}]},"categoriasDespesa":{"deputadoId":204358,"totalGasto":1817658.75,"totalCategorias":11,"categorias":[{"categoria":"DIVULGAÇÃO DA ATIVIDADE PARLAMENTAR.","totalGasto":854197.2,"quantidadeDespesas":102,"percentual":46.99},{"categoria":"LOCAÇÃO OU FRETAMENTO DE VEÍCULOS AUTOMOTORES","totalGasto":315400,"quantidadeDespesas":60,"percentual":17.35},{"categoria":"COMBUSTÍVEIS E LUBRIFICANTES.","totalGasto":224857.47,"quantidadeDespesas":63,"percentual":12.37},{"categoria":"PASSAGEM AÉREA - SIGEPA","totalGasto":175160.57,"quantidadeDespesas":235,"percentual":9.64},{"categoria":"MANUTENÇÃO DE ESCRITÓRIO DE APOIO À ATIVIDADE PARLAMENTAR","totalGasto":170291.08,"quantidadeDespesas":182,"percentual":9.37},{"categoria":"TELEFONIA","totalGasto":31392.73,"quantidadeDespesas":101,"percentual":1.73},{"categoria":"HOSPEDAGEM ,EXCETO DO PARLAMENTAR NO DISTRITO FEDERAL.","totalGasto":19484.15,"quantidadeDespesas":21,"percentual":1.07},{"categoria":"PASSAGEM AÉREA - REEMBOLSO","totalGasto":15313.89,"quantidadeDespesas":5,"percentual":0.84},{"categoria":"SERVIÇO DE SEGURANÇA PRESTADO POR EMPRESA ESPECIALIZADA.","totalGasto":11225.38,"quantidadeDespesas":35,"percentual":0.62},{"categoria":"SERVIÇO DE TÁXI, PEDÁGIO E ESTACIONAMENTO","totalGasto":179.5,"quantidadeDespesas":2,"percentual":0.01},{"categoria":"FORNECIMENTO DE ALIMENTAÇÃO DO PARLAMENTAR","totalGasto":156.78,"quantidadeDespesas":2,"percentual":0.01}]}}
