{"deputadoId":204474,"eixos":{"id":204474,"nome":"Juarez Costa","foto":"https://www.camara.leg.br/internet/deputado/bandep/204474.jpg","partido":"REPUBLIC","uf":"MT","totalProposicoes":208,"eixoPredominante":"social","eixos":[{"eixo":"social","total":73},{"eixo":"economico","total":72},{"eixo":"administrativo","total":59}],"termos":[{"termo":"Frente","frequencia":116,"peso":5},{"termo":"Registro","frequencia":80,"peso":4},{"termo":"Defesa","frequencia":49,"peso":3},{"termo":"Mista","frequencia":47,"peso":3},{"termo":"Administração Pública","frequencia":46,"peso":2},{"termo":"Criação","frequencia":40,"peso":2},{"termo":"Constituicao Federal 1988","frequencia":38,"peso":2},{"termo":"Direitos Humanos e Minorias","frequencia":36,"peso":2},{"termo":"Finanças Públicas e Orçamento","frequencia":32,"peso":2},{"termo":"Sessao","frequencia":32,"peso":2},{"termo":"Solene","frequencia":32,"peso":2},{"termo":"Trabalho e Emprego","frequencia":32,"peso":2},{"termo":"Deputados","frequencia":28,"peso":2},{"termo":"Saúde","frequencia":28,"peso":2}]},"custoBeneficio":{"deputadoId":204474,"nome":"Juarez Costa","partido":"REPUBLICANOS","uf":"MT","urlFoto":"https://www.camara.leg.br/internet/deputado/bandep/204474.jpg","gastoTotal":1263727.51,"totalProposicoes":251,"scoreBeneficio":332.99,"scoreCustoBeneficio":26.3498,"presencaPlenario":{"totalSessoes":322,"presencas":264,"ausenciasJustificadas":58,"ausenciasNaoJustificadas":0,"percentualPresenca":81.99},"formula":{"proposicao":1,"presencaPlenario":1,"escala":100000},"baseCustoReduzida":false,"posicaoGeral":451,"faixa":"Atenção"},"fornecedores":{"deputadoId":204474,"totalGasto":1263727.51,"totalFornecedores":171,"fornecedores":[{"fornecedor":"MB Prodruções","cnpjCpf":"142.002.390/0011-0","totalGasto":557419.4,"transacoes":31,"ticketMedio":17981.27,"percentual":44.11,"deputadosMesmoPartido":1,"alertaConcentracao":true,"alertaMesmoPartido":false},{"fornecedor":"MS CAR ALUGUEL DE VEICULOS LTDA","cnpjCpf":"236.473.030/0010-4","totalGasto":195133.3,"transacoes":19,"ticketMedio":10270.17,"percentual":15.44,"deputadosMesmoPartido":1,"alertaConcentracao":false,"alertaMesmoPartido":false},{"fornecedor":"REAVEL VEICULOS EIRELI","cnpjCpf":"302.605.380/0010-4","totalGasto":69319.36,"transacoes":8,"ticketMedio":8664.92,"percentual":5.49,"deputadosMesmoPartido":1,"alertaConcentracao":false,"alertaMesmoPartido":false},{"fornecedor":"TAM","cnpjCpf":null,"totalGasto":51507.1,"transacoes":64,"ticketMedio":804.8,"percentual":4.08,"deputadosMesmoPartido":0,"alertaConcentracao":false,"alertaMesmoPartido":false},{"fornecedor":"BSB ALUGUEL DE CARROS LTDA","cnpjCpf":"236.473.030/0010-4","totalGasto":47870.97,"transacoes":12,"ticketMedio":3989.25,"percentual":3.79,"deputadosMesmoPartido":1,"alertaConcentracao":false,"alertaMesmoPartido":false},{"fornecedor":"AZUL","cnpjCpf":null,"totalGasto":43687.02,"transacoes":43,"ticketMedio":1015.98,"percentual":3.46,"deputadosMesmoPartido":0,"alertaConcentracao":false,"alertaMesmoPartido":false},{"fornecedor":"VALDIR AFONSO CESCO","cnpjCpf":"296.713.539/91  -","totalGasto":38500,"transacoes":11,"ticketMedio":3500,"percentual":3.05,"deputadosMesmoPartido":1,"alertaConcentracao":false,"alertaMesmoPartido":false},{"fornecedor":"PAIAGUAS HOTEIS LTDA","cnpjCpf":"019.821.560/0018-8","totalGasto":29219.53,"transacoes":37,"ticketMedio":789.72,"percentual":2.31,"deputadosMesmoPartido":1,"alertaConcentracao":false,"alertaMesmoPartido":false}]},"categoriasDespesa":{"deputadoId":204474,"totalGasto":1263727.51,"totalCategorias":10,"categorias":[{"categoria":"DIVULGAÇÃO DA ATIVIDADE PARLAMENTAR.","totalGasto":579169.4,"quantidadeDespesas":46,"percentual":45.83},{"categoria":"LOCAÇÃO OU FRETAMENTO DE VEÍCULOS AUTOMOTORES","totalGasto":321023.63,"quantidadeDespesas":40,"percentual":25.4},{"categoria":"MANUTENÇÃO DE ESCRITÓRIO DE APOIO À ATIVIDADE PARLAMENTAR","totalGasto":126024.76,"quantidadeDespesas":102,"percentual":9.97},{"categoria":"PASSAGEM AÉREA - SIGEPA","totalGasto":108204.3,"quantidadeDespesas":121,"percentual":8.56},{"categoria":"COMBUSTÍVEIS E LUBRIFICANTES.","totalGasto":86123.79,"quantidadeDespesas":392,"percentual":6.82},{"categoria":"HOSPEDAGEM ,EXCETO DO PARLAMENTAR NO DISTRITO FEDERAL.","totalGasto":34689.53,"quantidadeDespesas":51,"percentual":2.75},{"categoria":"TELEFONIA","totalGasto":5632.9,"quantidadeDespesas":69,"percentual":0.45},{"categoria":"FORNECIMENTO DE ALIMENTAÇÃO DO PARLAMENTAR","totalGasto":1657.09,"quantidadeDespesas":18,"percentual":0.13},{"categoria":"PASSAGENS TERRESTRES, MARÍTIMAS OU FLUVIAIS","totalGasto":1078.81,"quantidadeDespesas":6,"percentual":0.09},{"categoria":"SERVIÇOS POSTAIS","totalGasto":123.3,"quantidadeDespesas":1,"percentual":0.01}]}}
