{"deputadoId":204566,"eixos":{"id":204566,"nome":"Marreca Filho","foto":"https://www.camara.leg.br/internet/deputado/bandep/204566.jpg","partido":"PRD","uf":"MA","totalProposicoes":316,"eixoPredominante":"social","eixos":[{"eixo":"social","total":82},{"eixo":"economico","total":76},{"eixo":"saude","total":71}],"termos":[{"termo":"Frente","frequencia":247,"peso":5},{"termo":"Registro","frequencia":151,"peso":4},{"termo":"Defesa","frequencia":107,"peso":3},{"termo":"Mista","frequencia":105,"peso":3},{"termo":"Criação","frequencia":64,"peso":2},{"termo":"Saúde","frequencia":59,"peso":2},{"termo":"Deputados","frequencia":44,"peso":1},{"termo":"Finanças Públicas e Orçamento","frequencia":40,"peso":1},{"termo":"Constituicao Federal 1988","frequencia":32,"peso":1},{"termo":"Sessao","frequencia":30,"peso":1},{"termo":"Solene","frequencia":30,"peso":1},{"termo":"Realizacao","frequencia":29,"peso":1},{"termo":"Administração Pública","frequencia":24,"peso":1},{"termo":"Trabalho e Emprego","frequencia":24,"peso":1}]},"custoBeneficio":{"deputadoId":204566,"nome":"Marreca Filho","partido":"PRD","uf":"MA","urlFoto":"https://www.camara.leg.br/internet/deputado/bandep/204566.jpg","gastoTotal":1532300.24,"totalProposicoes":409,"scoreBeneficio":487.66,"scoreCustoBeneficio":31.8254,"presencaPlenario":{"totalSessoes":314,"presencas":247,"ausenciasJustificadas":47,"ausenciasNaoJustificadas":20,"percentualPresenca":78.66},"formula":{"proposicao":1,"presencaPlenario":1,"escala":100000},"baseCustoReduzida":false,"posicaoGeral":383,"faixa":"Atenção"},"fornecedores":{"deputadoId":204566,"totalGasto":1532300.24,"totalFornecedores":151,"fornecedores":[{"fornecedor":"STV COMUNICACAO LTDA","cnpjCpf":"151.399.120/0011-6","totalGasto":256800,"transacoes":29,"ticketMedio":8855.17,"percentual":16.76,"deputadosMesmoPartido":1,"alertaConcentracao":false,"alertaMesmoPartido":false},{"fornecedor":"TAM","cnpjCpf":null,"totalGasto":172812.33,"transacoes":220,"ticketMedio":785.51,"percentual":11.28,"deputadosMesmoPartido":0,"alertaConcentracao":false,"alertaMesmoPartido":false},{"fornecedor":"LUANY DE OLIVEIRA PESTANA","cnpjCpf":"526.424.550/0010-4","totalGasto":160500,"transacoes":19,"ticketMedio":8447.37,"percentual":10.47,"deputadosMesmoPartido":1,"alertaConcentracao":false,"alertaMesmoPartido":false},{"fornecedor":"CATI CVI LTDA","cnpjCpf":"333.362.110/0015-9","totalGasto":133320,"transacoes":4,"ticketMedio":33330,"percentual":8.7,"deputadosMesmoPartido":1,"alertaConcentracao":false,"alertaMesmoPartido":false},{"fornecedor":"AGUIAR LOCAÇÃO E TURISMO","cnpjCpf":"079.221.390/0013-1","totalGasto":74802.21,"transacoes":14,"ticketMedio":5343.02,"percentual":4.88,"deputadosMesmoPartido":1,"alertaConcentracao":false,"alertaMesmoPartido":false},{"fornecedor":"GOL","cnpjCpf":null,"totalGasto":73271.02,"transacoes":77,"ticketMedio":951.57,"percentual":4.78,"deputadosMesmoPartido":0,"alertaConcentracao":false,"alertaMesmoPartido":false},{"fornecedor":"LOCAUTOS LOCADORA DE VEICULOS LTDA ME","cnpjCpf":"171.425.270/0015-3","totalGasto":67299.2,"transacoes":8,"ticketMedio":8412.4,"percentual":4.39,"deputadosMesmoPartido":1,"alertaConcentracao":false,"alertaMesmoPartido":false},{"fornecedor":"T E R Produçôes e Eventos LTDA","cnpjCpf":"303.120.010/0013-2","totalGasto":57800,"transacoes":11,"ticketMedio":5254.55,"percentual":3.77,"deputadosMesmoPartido":1,"alertaConcentracao":false,"alertaMesmoPartido":false}]},"categoriasDespesa":{"deputadoId":204566,"totalGasto":1532300.24,"totalCategorias":9,"categorias":[{"categoria":"DIVULGAÇÃO DA ATIVIDADE PARLAMENTAR.","totalGasto":820535.24,"quantidadeDespesas":158,"percentual":53.55},{"categoria":"PASSAGEM AÉREA - SIGEPA","totalGasto":271871.29,"quantidadeDespesas":335,"percentual":17.74},{"categoria":"LOCAÇÃO OU FRETAMENTO DE VEÍCULOS AUTOMOTORES","totalGasto":184589.37,"quantidadeDespesas":30,"percentual":12.05},{"categoria":"COMBUSTÍVEIS E LUBRIFICANTES.","totalGasto":169612.79,"quantidadeDespesas":312,"percentual":11.07},{"categoria":"MANUTENÇÃO DE ESCRITÓRIO DE APOIO À ATIVIDADE PARLAMENTAR","totalGasto":65721.8,"quantidadeDespesas":69,"percentual":4.29},{"categoria":"TELEFONIA","totalGasto":19065.72,"quantidadeDespesas":82,"percentual":1.24},{"categoria":"PASSAGENS TERRESTRES, MARÍTIMAS OU FLUVIAIS","totalGasto":480,"quantidadeDespesas":1,"percentual":0.03},{"categoria":"HOSPEDAGEM ,EXCETO DO PARLAMENTAR NO DISTRITO FEDERAL.","totalGasto":250,"quantidadeDespesas":1,"percentual":0.02},{"categoria":"FORNECIMENTO DE ALIMENTAÇÃO DO PARLAMENTAR","totalGasto":174.03,"quantidadeDespesas":2,"percentual":0.01}]}}
