{"deputadoId":204518,"eixos":{"id":204518,"nome":"Dr. Frederico","foto":"https://www.camara.leg.br/internet/deputado/bandep/204518.jpg","partido":"PRD","uf":"MG","totalProposicoes":763,"eixoPredominante":"saude","eixos":[{"eixo":"saude","total":486},{"eixo":"social","total":306},{"eixo":"economico","total":303}],"termos":[{"termo":"Saúde","frequencia":519,"peso":5},{"termo":"Administração Pública","frequencia":334,"peso":4},{"termo":"Finanças Públicas e Orçamento","frequencia":212,"peso":3},{"termo":"Sessao","frequencia":160,"peso":2},{"termo":"Solene","frequencia":157,"peso":2},{"termo":"Deputados","frequencia":147,"peso":2},{"termo":"Frente","frequencia":136,"peso":2},{"termo":"Realizacao","frequencia":136,"peso":2},{"termo":"Direitos Humanos e Minorias","frequencia":128,"peso":2},{"termo":"Ministro","frequencia":102,"peso":1},{"termo":"Defesa e Segurança","frequencia":100,"peso":1},{"termo":"Criação","frequencia":96,"peso":1},{"termo":"Previdência e Assistência Social","frequencia":92,"peso":1},{"termo":"Educação","frequencia":86,"peso":1}]},"custoBeneficio":{"deputadoId":204518,"nome":"Dr. Frederico","partido":"PL","uf":"MG","urlFoto":"https://www.camara.leg.br/internet/deputado/bandep/204518.jpg","gastoTotal":1651122.7,"totalProposicoes":938,"scoreBeneficio":1033.38,"scoreCustoBeneficio":62.5865,"presencaPlenario":{"totalSessoes":390,"presencas":372,"ausenciasJustificadas":8,"ausenciasNaoJustificadas":10,"percentualPresenca":95.38},"formula":{"proposicao":1,"presencaPlenario":1,"escala":100000},"baseCustoReduzida":false,"posicaoGeral":159,"faixa":"Muito bom"},"fornecedores":{"deputadoId":204518,"totalGasto":1651122.7,"totalFornecedores":67,"fornecedores":[{"fornecedor":"A.M.Silva Comunicação","cnpjCpf":"094.146.170/0012-8","totalGasto":405000,"transacoes":39,"ticketMedio":10384.62,"percentual":24.53,"deputadosMesmoPartido":1,"alertaConcentracao":false,"alertaMesmoPartido":false},{"fornecedor":"TARGET RENT A CAR LTDA","cnpjCpf":"216.526.720/0015-1","totalGasto":202386,"transacoes":57,"ticketMedio":3550.63,"percentual":12.26,"deputadosMesmoPartido":1,"alertaConcentracao":false,"alertaMesmoPartido":false},{"fornecedor":"AUTO POSTO CANADA LTDA EPP","cnpjCpf":"026.445.770/0016-1","totalGasto":114649.18,"transacoes":33,"ticketMedio":3474.22,"percentual":6.94,"deputadosMesmoPartido":1,"alertaConcentracao":false,"alertaMesmoPartido":false},{"fornecedor":"PANTANAL VEÍCULOS LTDA","cnpjCpf":"073.193.230/0019-1","totalGasto":104400,"transacoes":24,"ticketMedio":4350,"percentual":6.32,"deputadosMesmoPartido":33,"alertaConcentracao":false,"alertaMesmoPartido":true},{"fornecedor":"MATHEUS NEVES DE MEDEIROS","cnpjCpf":"525.311.930/0010-0","totalGasto":102500,"transacoes":30,"ticketMedio":3416.67,"percentual":6.21,"deputadosMesmoPartido":1,"alertaConcentracao":false,"alertaMesmoPartido":false},{"fornecedor":"AZUL","cnpjCpf":null,"totalGasto":74055.65,"transacoes":86,"ticketMedio":861.11,"percentual":4.49,"deputadosMesmoPartido":0,"alertaConcentracao":false,"alertaMesmoPartido":false},{"fornecedor":"Jornal Panorama Ltda - ME","cnpjCpf":"085.603.980/0012-2","totalGasto":67500,"transacoes":29,"ticketMedio":2327.59,"percentual":4.09,"deputadosMesmoPartido":1,"alertaConcentracao":false,"alertaMesmoPartido":false},{"fornecedor":"Novacar Locadora de Veículos Ltda","cnpjCpf":"193.747.910/0014-8","totalGasto":60860,"transacoes":13,"ticketMedio":4681.54,"percentual":3.69,"deputadosMesmoPartido":17,"alertaConcentracao":false,"alertaMesmoPartido":true}]},"categoriasDespesa":{"deputadoId":204518,"totalGasto":1651122.7,"totalCategorias":9,"categorias":[{"categoria":"DIVULGAÇÃO DA ATIVIDADE PARLAMENTAR.","totalGasto":783620,"quantidadeDespesas":217,"percentual":47.46},{"categoria":"LOCAÇÃO OU FRETAMENTO DE VEÍCULOS AUTOMOTORES","totalGasto":426446,"quantidadeDespesas":104,"percentual":25.83},{"categoria":"COMBUSTÍVEIS E LUBRIFICANTES.","totalGasto":165831.93,"quantidadeDespesas":103,"percentual":10.04},{"categoria":"MANUTENÇÃO DE ESCRITÓRIO DE APOIO À ATIVIDADE PARLAMENTAR","totalGasto":131526.64,"quantidadeDespesas":152,"percentual":7.97},{"categoria":"PASSAGEM AÉREA - SIGEPA","totalGasto":101714.4,"quantidadeDespesas":138,"percentual":6.16},{"categoria":"TELEFONIA","totalGasto":18075.53,"quantidadeDespesas":89,"percentual":1.09},{"categoria":"HOSPEDAGEM ,EXCETO DO PARLAMENTAR NO DISTRITO FEDERAL.","totalGasto":13499.44,"quantidadeDespesas":42,"percentual":0.82},{"categoria":"SERVIÇO DE TÁXI, PEDÁGIO E ESTACIONAMENTO","totalGasto":9151.96,"quantidadeDespesas":38,"percentual":0.55},{"categoria":"SERVIÇO DE SEGURANÇA PRESTADO POR EMPRESA ESPECIALIZADA.","totalGasto":1256.8,"quantidadeDespesas":8,"percentual":0.08}]}}
