{"deputadoId":209189,"eixos":{"id":209189,"nome":"Joseildo Ramos","foto":"https://www.camara.leg.br/internet/deputado/bandep/209189.jpg","partido":"PT","uf":"BA","totalProposicoes":307,"eixoPredominante":"economico","eixos":[{"eixo":"economico","total":98},{"eixo":"social","total":92},{"eixo":"administrativo","total":78}],"termos":[{"termo":"Frente","frequencia":130,"peso":5},{"termo":"Registro","frequencia":91,"peso":4},{"termo":"Realizacao","frequencia":80,"peso":4},{"termo":"Sessao","frequencia":73,"peso":3},{"termo":"Defesa","frequencia":72,"peso":3},{"termo":"Solene","frequencia":70,"peso":3},{"termo":"Mista","frequencia":67,"peso":3},{"termo":"Criação","frequencia":59,"peso":3},{"termo":"Administração Pública","frequencia":52,"peso":2},{"termo":"Deputados","frequencia":41,"peso":2},{"termo":"Finanças Públicas e Orçamento","frequencia":40,"peso":2},{"termo":"Direitos Humanos e Minorias","frequencia":28,"peso":2},{"termo":"Indústria Comercio e Serviços","frequencia":28,"peso":2},{"termo":"Saúde","frequencia":28,"peso":2}]},"custoBeneficio":{"deputadoId":209189,"nome":"Joseildo Ramos","partido":"PT","uf":"BA","urlFoto":"https://www.camara.leg.br/internet/deputado/bandep/209189.jpg","gastoTotal":1756912.77,"totalProposicoes":342,"scoreBeneficio":438.41,"scoreCustoBeneficio":24.9534,"presencaPlenario":{"totalSessoes":390,"presencas":376,"ausenciasJustificadas":8,"ausenciasNaoJustificadas":6,"percentualPresenca":96.41},"formula":{"proposicao":1,"presencaPlenario":1,"escala":100000},"baseCustoReduzida":false,"posicaoGeral":462,"faixa":"Atenção"},"fornecedores":{"deputadoId":209189,"totalGasto":1756912.77,"totalFornecedores":301,"fornecedores":[{"fornecedor":"NATIVA SERVICOS EIRELI - ME","cnpjCpf":"172.801.850/0013-8","totalGasto":424000,"transacoes":38,"ticketMedio":11157.89,"percentual":24.13,"deputadosMesmoPartido":2,"alertaConcentracao":false,"alertaMesmoPartido":true},{"fornecedor":"LUCIANO MIGNAC CUMMING","cnpjCpf":"085.124.695/87  -","totalGasto":161878.99,"transacoes":32,"ticketMedio":5058.72,"percentual":9.21,"deputadosMesmoPartido":1,"alertaConcentracao":false,"alertaMesmoPartido":false},{"fornecedor":"ANDRE LUIZ MACHADO DOS SANTOS","cnpjCpf":"232.742.700/0019-6","totalGasto":151500,"transacoes":20,"ticketMedio":7575,"percentual":8.62,"deputadosMesmoPartido":1,"alertaConcentracao":false,"alertaMesmoPartido":false},{"fornecedor":"RADIO REGIONAL DE ALAGOINHAS","cnpjCpf":"137.551.940/0018-7","totalGasto":84000,"transacoes":20,"ticketMedio":4200,"percentual":4.78,"deputadosMesmoPartido":1,"alertaConcentracao":false,"alertaMesmoPartido":false},{"fornecedor":"TAM","cnpjCpf":null,"totalGasto":75491.58,"transacoes":146,"ticketMedio":517.07,"percentual":4.3,"deputadosMesmoPartido":0,"alertaConcentracao":false,"alertaMesmoPartido":false},{"fornecedor":"CARLOS MAIA D'OLIVEIRA","cnpjCpf":"175.471.805/15  -","totalGasto":74700,"transacoes":30,"ticketMedio":2490,"percentual":4.25,"deputadosMesmoPartido":1,"alertaConcentracao":false,"alertaMesmoPartido":false},{"fornecedor":"GOL","cnpjCpf":null,"totalGasto":70247.12,"transacoes":84,"ticketMedio":836.28,"percentual":4,"deputadosMesmoPartido":0,"alertaConcentracao":false,"alertaMesmoPartido":false},{"fornecedor":"THAYLANE GLEYCE ARAUJO SANTOS","cnpjCpf":"497.611.850/0014-6","totalGasto":53000,"transacoes":23,"ticketMedio":2304.35,"percentual":3.02,"deputadosMesmoPartido":1,"alertaConcentracao":false,"alertaMesmoPartido":false}]},"categoriasDespesa":{"deputadoId":209189,"totalGasto":1756912.77,"totalCategorias":13,"categorias":[{"categoria":"DIVULGAÇÃO DA ATIVIDADE PARLAMENTAR.","totalGasto":543173.66,"quantidadeDespesas":151,"percentual":30.92},{"categoria":"LOCAÇÃO OU FRETAMENTO DE VEÍCULOS AUTOMOTORES","totalGasto":446099.22,"quantidadeDespesas":49,"percentual":25.39},{"categoria":"MANUTENÇÃO DE ESCRITÓRIO DE APOIO À ATIVIDADE PARLAMENTAR","totalGasto":310262.56,"quantidadeDespesas":143,"percentual":17.66},{"categoria":"COMBUSTÍVEIS E LUBRIFICANTES.","totalGasto":227716.79,"quantidadeDespesas":739,"percentual":12.96},{"categoria":"PASSAGEM AÉREA - SIGEPA","totalGasto":156734.08,"quantidadeDespesas":243,"percentual":8.92},{"categoria":"SERVIÇO DE TÁXI, PEDÁGIO E ESTACIONAMENTO","totalGasto":22865.51,"quantidadeDespesas":39,"percentual":1.3},{"categoria":"HOSPEDAGEM ,EXCETO DO PARLAMENTAR NO DISTRITO FEDERAL.","totalGasto":21024.48,"quantidadeDespesas":52,"percentual":1.2},{"categoria":"FORNECIMENTO DE ALIMENTAÇÃO DO PARLAMENTAR","totalGasto":17952.53,"quantidadeDespesas":238,"percentual":1.02},{"categoria":"TELEFONIA","totalGasto":7408.66,"quantidadeDespesas":93,"percentual":0.42},{"categoria":"PASSAGEM AÉREA - REEMBOLSO","totalGasto":2723.22,"quantidadeDespesas":1,"percentual":0.16},{"categoria":"PASSAGENS TERRESTRES, MARÍTIMAS OU FLUVIAIS","totalGasto":483.67,"quantidadeDespesas":2,"percentual":0.03},{"categoria":"PASSAGEM AÉREA - RPA","totalGasto":433.39,"quantidadeDespesas":3,"percentual":0.02}]}}
