{"deputadoId":220697,"eixos":{"id":220697,"nome":"Jadyel Alencar","foto":"https://www.camara.leg.br/internet/deputado/bandep/220697.jpg","partido":"REPUBLIC","uf":"PI","totalProposicoes":594,"eixoPredominante":"economico","eixos":[{"eixo":"economico","total":185},{"eixo":"social","total":164},{"eixo":"educacao","total":108}],"termos":[{"termo":"Frente","frequencia":288,"peso":5},{"termo":"Registro","frequencia":188,"peso":4},{"termo":"Mista","frequencia":137,"peso":3},{"termo":"Realizacao","frequencia":127,"peso":3},{"termo":"Defesa","frequencia":117,"peso":3},{"termo":"Criação","frequencia":114,"peso":2},{"termo":"Sessao","frequencia":113,"peso":2},{"termo":"Solene","frequencia":111,"peso":2},{"termo":"Deputados","frequencia":106,"peso":2},{"termo":"Administração Pública","frequencia":100,"peso":2},{"termo":"Saúde","frequencia":80,"peso":2},{"termo":"Finanças Públicas e Orçamento","frequencia":64,"peso":2},{"termo":"Meio Ambiente e Desenvolvimento","frequencia":64,"peso":2},{"termo":"Direitos Humanos e Minorias","frequencia":60,"peso":2}]},"custoBeneficio":{"deputadoId":220697,"nome":"Jadyel Alencar","partido":"REPUBLICANOS","uf":"PI","urlFoto":"https://www.camara.leg.br/internet/deputado/bandep/220697.jpg","gastoTotal":1732766.14,"totalProposicoes":744,"scoreBeneficio":832.95,"scoreCustoBeneficio":48.0705,"presencaPlenario":{"totalSessoes":389,"presencas":346,"ausenciasJustificadas":18,"ausenciasNaoJustificadas":25,"percentualPresenca":88.95},"formula":{"proposicao":1,"presencaPlenario":1,"escala":100000},"baseCustoReduzida":false,"posicaoGeral":225,"faixa":"Muito bom"},"fornecedores":{"deputadoId":220697,"totalGasto":1732766.14,"totalFornecedores":68,"fornecedores":[{"fornecedor":"ESTAÇÃO I ESTUDO CRIATIVO LTDA","cnpjCpf":"497.748.830/0018-6","totalGasto":243000,"transacoes":8,"ticketMedio":30375,"percentual":14.02,"deputadosMesmoPartido":1,"alertaConcentracao":false,"alertaMesmoPartido":false},{"fornecedor":"AUTO LESTE LTDA","cnpjCpf":"091.165.410/0015-4","totalGasto":228000,"transacoes":19,"ticketMedio":12000,"percentual":13.16,"deputadosMesmoPartido":1,"alertaConcentracao":false,"alertaMesmoPartido":false},{"fornecedor":"TAM","cnpjCpf":null,"totalGasto":166159.84,"transacoes":253,"ticketMedio":656.76,"percentual":9.59,"deputadosMesmoPartido":0,"alertaConcentracao":false,"alertaMesmoPartido":false},{"fornecedor":"ROCHA FILHO","cnpjCpf":"024.183.050/0014-3","totalGasto":100360,"transacoes":30,"ticketMedio":3345.33,"percentual":5.79,"deputadosMesmoPartido":1,"alertaConcentracao":false,"alertaMesmoPartido":false},{"fornecedor":"J DE ARAUJO S E SILVA","cnpjCpf":"474.556.200/0018-9","totalGasto":68250,"transacoes":7,"ticketMedio":9750,"percentual":3.94,"deputadosMesmoPartido":1,"alertaConcentracao":false,"alertaMesmoPartido":false},{"fornecedor":"ESTIMATIVA EDITORA E COMUNICACAO LTDA","cnpjCpf":"226.755.430/0014-1","totalGasto":65000,"transacoes":26,"ticketMedio":2500,"percentual":3.75,"deputadosMesmoPartido":1,"alertaConcentracao":false,"alertaMesmoPartido":false},{"fornecedor":"grafica imprimex comunicação visual","cnpjCpf":"329.721.570/0017-5","totalGasto":65000,"transacoes":4,"ticketMedio":16250,"percentual":3.75,"deputadosMesmoPartido":1,"alertaConcentracao":false,"alertaMesmoPartido":false},{"fornecedor":"ALFA COMUNICAÇÃO E MARKETING DIGITAL LTDA","cnpjCpf":"412.334.830/0015-1","totalGasto":60500,"transacoes":36,"ticketMedio":1680.56,"percentual":3.49,"deputadosMesmoPartido":3,"alertaConcentracao":false,"alertaMesmoPartido":true}]},"categoriasDespesa":{"deputadoId":220697,"totalGasto":1732766.14,"totalCategorias":10,"categorias":[{"categoria":"DIVULGAÇÃO DA ATIVIDADE PARLAMENTAR.","totalGasto":1095059.4,"quantidadeDespesas":225,"percentual":63.2},{"categoria":"LOCAÇÃO OU FRETAMENTO DE VEÍCULOS AUTOMOTORES","totalGasto":228000,"quantidadeDespesas":19,"percentual":13.16},{"categoria":"PASSAGEM AÉREA - SIGEPA","totalGasto":215742.34,"quantidadeDespesas":315,"percentual":12.45},{"categoria":"MANUTENÇÃO DE ESCRITÓRIO DE APOIO À ATIVIDADE PARLAMENTAR","totalGasto":144465.32,"quantidadeDespesas":72,"percentual":8.34},{"categoria":"COMBUSTÍVEIS E LUBRIFICANTES.","totalGasto":30041.49,"quantidadeDespesas":120,"percentual":1.73},{"categoria":"HOSPEDAGEM ,EXCETO DO PARLAMENTAR NO DISTRITO FEDERAL.","totalGasto":12977.15,"quantidadeDespesas":15,"percentual":0.75},{"categoria":"PASSAGEM AÉREA - REEMBOLSO","totalGasto":5111.69,"quantidadeDespesas":2,"percentual":0.3},{"categoria":"SERVIÇO DE TÁXI, PEDÁGIO E ESTACIONAMENTO","totalGasto":1064.05,"quantidadeDespesas":33,"percentual":0.06},{"categoria":"FORNECIMENTO DE ALIMENTAÇÃO DO PARLAMENTAR","totalGasto":166.68,"quantidadeDespesas":2,"percentual":0.01},{"categoria":"TELEFONIA","totalGasto":138.02,"quantidadeDespesas":32,"percentual":0.01}]}}
