{"deputadoId":225730,"eixos":{"id":225730,"nome":"Enfermeira Ana Paula","foto":"https://www.camara.leg.br/internet/deputado/bandep/225730.jpg","partido":"PODE","uf":"CE","totalProposicoes":113,"eixoPredominante":"saude","eixos":[{"eixo":"saude","total":150},{"eixo":"social","total":97},{"eixo":"seguranca","total":46}],"termos":[{"termo":"Saúde","frequencia":129,"peso":5},{"termo":"Trabalho e Emprego","frequencia":100,"peso":4},{"termo":"Frente","frequencia":38,"peso":2},{"termo":"Enfermagem","frequencia":37,"peso":2},{"termo":"Criação","frequencia":30,"peso":2},{"termo":"Direitos Humanos e Minorias","frequencia":28,"peso":2},{"termo":"Registro","frequencia":27,"peso":2},{"termo":"Enfermeiro","frequencia":26,"peso":2},{"termo":"Diretrizes","frequencia":24,"peso":1},{"termo":"Mista","frequencia":19,"peso":1},{"termo":"Profissionais","frequencia":19,"peso":1},{"termo":"Defesa","frequencia":18,"peso":1},{"termo":"Realizacao","frequencia":17,"peso":1},{"termo":"Sessao","frequencia":17,"peso":1}]},"custoBeneficio":{"deputadoId":225730,"nome":"Enfermeira Ana Paula","partido":"PODE","uf":"CE","urlFoto":"https://www.camara.leg.br/internet/deputado/bandep/225730.jpg","gastoTotal":811752.19,"totalProposicoes":215,"scoreBeneficio":215,"scoreCustoBeneficio":26.4859,"presencaPlenario":{"totalSessoes":0,"presencas":0,"ausenciasJustificadas":0,"ausenciasNaoJustificadas":0,"percentualPresenca":0},"formula":{"proposicao":1,"presencaPlenario":1,"escala":100000},"baseCustoReduzida":false,"posicaoGeral":448,"faixa":"Atenção"},"fornecedores":{"deputadoId":225730,"totalGasto":811752.19,"totalFornecedores":122,"fornecedores":[{"fornecedor":"G3 NETO SERVIÇOS EIRELI-ME","cnpjCpf":"113.052.350/0010-8","totalGasto":208125,"transacoes":17,"ticketMedio":12242.65,"percentual":25.64,"deputadosMesmoPartido":1,"alertaConcentracao":false,"alertaMesmoPartido":false},{"fornecedor":"JOSE ROBERTO DE SOUSA NETO","cnpjCpf":"535.208.420/0013-0","totalGasto":180000,"transacoes":9,"ticketMedio":20000,"percentual":22.17,"deputadosMesmoPartido":1,"alertaConcentracao":false,"alertaMesmoPartido":false},{"fornecedor":"NF COMUNICAÇÃO DIGITAL LTDA","cnpjCpf":"535.208.420/0013-0","totalGasto":98166.7,"transacoes":4,"ticketMedio":24541.68,"percentual":12.09,"deputadosMesmoPartido":1,"alertaConcentracao":false,"alertaMesmoPartido":false},{"fornecedor":"TAM","cnpjCpf":null,"totalGasto":55764.83,"transacoes":64,"ticketMedio":871.33,"percentual":6.87,"deputadosMesmoPartido":0,"alertaConcentracao":false,"alertaMesmoPartido":false},{"fornecedor":"LARA PRODUÇÕES E FILMES LTDA","cnpjCpf":"102.126.190/0011-3","totalGasto":46395.5,"transacoes":3,"ticketMedio":15465.17,"percentual":5.72,"deputadosMesmoPartido":1,"alertaConcentracao":false,"alertaMesmoPartido":false},{"fornecedor":"SUPREMA MOBILIDADE LTDA","cnpjCpf":"248.943.970/0017-0","totalGasto":37366.67,"transacoes":10,"ticketMedio":3736.67,"percentual":4.6,"deputadosMesmoPartido":5,"alertaConcentracao":false,"alertaMesmoPartido":true},{"fornecedor":"coworking.etc.br","cnpjCpf":"273.622.640/0014-1","totalGasto":24166.67,"transacoes":5,"ticketMedio":4833.33,"percentual":2.98,"deputadosMesmoPartido":1,"alertaConcentracao":false,"alertaMesmoPartido":false},{"fornecedor":"L. CARLOS TOMAZ ABJAD COMUNICACAO MAGNETICA","cnpjCpf":"643.764.910/0015-2","totalGasto":17733.34,"transacoes":2,"ticketMedio":8866.67,"percentual":2.18,"deputadosMesmoPartido":1,"alertaConcentracao":false,"alertaMesmoPartido":false}]},"categoriasDespesa":{"deputadoId":225730,"totalGasto":811752.19,"totalCategorias":10,"categorias":[{"categoria":"DIVULGAÇÃO DA ATIVIDADE PARLAMENTAR.","totalGasto":369295.54,"quantidadeDespesas":20,"percentual":45.49},{"categoria":"LOCAÇÃO OU FRETAMENTO DE VEÍCULOS AUTOMOTORES","totalGasto":257991.67,"quantidadeDespesas":28,"percentual":31.78},{"categoria":"COMBUSTÍVEIS E LUBRIFICANTES.","totalGasto":73481.27,"quantidadeDespesas":289,"percentual":9.05},{"categoria":"PASSAGEM AÉREA - SIGEPA","totalGasto":65186.82,"quantidadeDespesas":70,"percentual":8.03},{"categoria":"MANUTENÇÃO DE ESCRITÓRIO DE APOIO À ATIVIDADE PARLAMENTAR","totalGasto":34467.14,"quantidadeDespesas":23,"percentual":4.25},{"categoria":"HOSPEDAGEM ,EXCETO DO PARLAMENTAR NO DISTRITO FEDERAL.","totalGasto":4394.44,"quantidadeDespesas":16,"percentual":0.54},{"categoria":"PASSAGEM AÉREA - REEMBOLSO","totalGasto":3347.89,"quantidadeDespesas":1,"percentual":0.41},{"categoria":"FORNECIMENTO DE ALIMENTAÇÃO DO PARLAMENTAR","totalGasto":2878.58,"quantidadeDespesas":40,"percentual":0.35},{"categoria":"AQUISIÇÃO DE TOKENS E CERTIFICADOS DIGITAIS","totalGasto":700,"quantidadeDespesas":3,"percentual":0.09},{"categoria":"TELEFONIA","totalGasto":8.84,"quantidadeDespesas":14,"percentual":0}]}}
