{"deputadoId":225846,"eixos":{"id":225846,"nome":"Itamar Paim","foto":"https://www.camara.leg.br/internet/deputado/bandep/225846.jpg","partido":"PL","uf":"PR","totalProposicoes":2,"eixoPredominante":"seguranca","eixos":[{"eixo":"seguranca","total":15},{"eixo":"social","total":4},{"eixo":"meio_ambiente","total":3}],"termos":[{"termo":"Direito Penal e Processual","frequencia":8,"peso":5},{"termo":"Direitos Humanos e Minorias","frequencia":8,"peso":5},{"termo":"Reducao","frequencia":5,"peso":4},{"termo":"Constituicao Federal 1988","frequencia":4,"peso":3},{"termo":"Crime Hediondo","frequencia":4,"peso":3},{"termo":"Meio Ambiente e Desenvolvimento","frequencia":4,"peso":3},{"termo":"Crueldade","frequencia":3,"peso":2},{"termo":"Acusado","frequencia":2,"peso":2},{"termo":"Animal","frequencia":2,"peso":2},{"termo":"Autor Processo Penal","frequencia":2,"peso":2},{"termo":"Carater Excepcional","frequencia":2,"peso":2},{"termo":"Constituicao","frequencia":2,"peso":2},{"termo":"Crime Contra a Vida","frequencia":2,"peso":2},{"termo":"Crime Violento","frequencia":2,"peso":2}]},"custoBeneficio":null,"fornecedores":{"deputadoId":225846,"totalGasto":1624.6,"totalFornecedores":7,"fornecedores":[{"fornecedor":"POSTO MARU S A - 2","cnpjCpf":"818.942.970/0026-9","totalGasto":373.18,"transacoes":1,"ticketMedio":373.18,"percentual":22.97,"deputadosMesmoPartido":2,"alertaConcentracao":false,"alertaMesmoPartido":true},{"fornecedor":"SERVICO NACIONAL DE APREND. COMERCIAL","cnpjCpf":"334.691.720/0164-4","totalGasto":300.18,"transacoes":3,"ticketMedio":100.06,"percentual":18.48,"deputadosMesmoPartido":48,"alertaConcentracao":false,"alertaMesmoPartido":true},{"fornecedor":"PHE HOTELARIA LTDA","cnpjCpf":"437.422.680/0010-1","totalGasto":284.09,"transacoes":1,"ticketMedio":284.09,"percentual":17.49,"deputadosMesmoPartido":1,"alertaConcentracao":false,"alertaMesmoPartido":false},{"fornecedor":"hotel slim guarapuava ltda","cnpjCpf":"355.223.790/0018-4","totalGasto":269.85,"transacoes":1,"ticketMedio":269.85,"percentual":16.61,"deputadosMesmoPartido":2,"alertaConcentracao":false,"alertaMesmoPartido":true},{"fornecedor":"REDE QUALITY COMERCIO DE COMBUSTIVEIS LTDA","cnpjCpf":"369.003.910/0057-1","totalGasto":234,"transacoes":1,"ticketMedio":234,"percentual":14.4,"deputadosMesmoPartido":14,"alertaConcentracao":false,"alertaMesmoPartido":true},{"fornecedor":"ESPLANADA EVENTOS RESTAURANTE E DELIVERY EIRELI","cnpjCpf":"433.674.340/0013-7","totalGasto":92.07,"transacoes":1,"ticketMedio":92.07,"percentual":5.67,"deputadosMesmoPartido":9,"alertaConcentracao":false,"alertaMesmoPartido":true},{"fornecedor":"ESMANIOTTO RESTAURANTE LTDA","cnpjCpf":"849.168.240/0010-4","totalGasto":71.23,"transacoes":1,"ticketMedio":71.23,"percentual":4.38,"deputadosMesmoPartido":1,"alertaConcentracao":false,"alertaMesmoPartido":false}]},"categoriasDespesa":{"deputadoId":225846,"totalGasto":1624.6,"totalCategorias":3,"categorias":[{"categoria":"COMBUSTÍVEIS E LUBRIFICANTES.","totalGasto":607.18,"quantidadeDespesas":2,"percentual":37.37},{"categoria":"HOSPEDAGEM ,EXCETO DO PARLAMENTAR NO DISTRITO FEDERAL.","totalGasto":553.94,"quantidadeDespesas":2,"percentual":34.1},{"categoria":"FORNECIMENTO DE ALIMENTAÇÃO DO PARLAMENTAR","totalGasto":463.48,"quantidadeDespesas":5,"percentual":28.53}]}}
