{"deputadoId":226553,"eixos":{"id":226553,"nome":"Eliane Braz","foto":"https://www.camara.leg.br/internet/deputado/bandep/226553.jpg","partido":"PSD","uf":"CE","totalProposicoes":8,"eixoPredominante":"economico","eixos":[{"eixo":"economico","total":22},{"eixo":"social","total":12},{"eixo":"seguranca","total":11}],"termos":[{"termo":"Economia","frequencia":9,"peso":5},{"termo":"Agricultura Pecuária Pesca e","frequencia":8,"peso":5},{"termo":"Meio Ambiente e Desenvolvimento","frequencia":8,"peso":5},{"termo":"Administração Pública","frequencia":4,"peso":3},{"termo":"Criação","frequencia":4,"peso":3},{"termo":"Defesa e Segurança","frequencia":4,"peso":3},{"termo":"Direito Penal e Processual","frequencia":4,"peso":3},{"termo":"Finanças Públicas e Orçamento","frequencia":4,"peso":3},{"termo":"Saúde","frequencia":4,"peso":3},{"termo":"Trabalho e Emprego","frequencia":4,"peso":3},{"termo":"Frente","frequencia":3,"peso":2},{"termo":"Registro","frequencia":3,"peso":2},{"termo":"Abuso","frequencia":2,"peso":2},{"termo":"Agricultor","frequencia":2,"peso":2}]},"custoBeneficio":{"deputadoId":226553,"nome":"Eliane Braz","partido":"PSD","uf":"CE","urlFoto":"https://www.camara.leg.br/internet/deputado/bandep/226553.jpg","gastoTotal":114344.94,"totalProposicoes":9,"scoreBeneficio":9,"scoreCustoBeneficio":7.8709,"presencaPlenario":{"totalSessoes":0,"presencas":0,"ausenciasJustificadas":0,"ausenciasNaoJustificadas":0,"percentualPresenca":0},"formula":{"proposicao":1,"presencaPlenario":1,"escala":100000},"baseCustoReduzida":false,"posicaoGeral":609,"faixa":"Baixo CxB"},"fornecedores":{"deputadoId":226553,"totalGasto":114344.94,"totalFornecedores":30,"fornecedores":[{"fornecedor":"TE MKT","cnpjCpf":"504.799.770/0010-1","totalGasto":20000,"transacoes":2,"ticketMedio":10000,"percentual":17.49,"deputadosMesmoPartido":2,"alertaConcentracao":false,"alertaMesmoPartido":true},{"fornecedor":"DELPHOS SERVICOS DE MARKETING E COMUNICACAO LTDA","cnpjCpf":"186.067.540/0015-5","totalGasto":16000,"transacoes":2,"ticketMedio":8000,"percentual":13.99,"deputadosMesmoPartido":2,"alertaConcentracao":false,"alertaMesmoPartido":true},{"fornecedor":"CONSULT NEGOCIOS IMOBILIARIOS","cnpjCpf":"465.568.650/0013-0","totalGasto":11000,"transacoes":2,"ticketMedio":5500,"percentual":9.62,"deputadosMesmoPartido":2,"alertaConcentracao":false,"alertaMesmoPartido":true},{"fornecedor":"SMART VEÍCULOS LTDA-ME","cnpjCpf":"291.391.110/0016-5","totalGasto":10881,"transacoes":3,"ticketMedio":3627,"percentual":9.52,"deputadosMesmoPartido":2,"alertaConcentracao":false,"alertaMesmoPartido":true},{"fornecedor":"CAROLINE MARIA VASCONCELOS","cnpjCpf":"366.231.670/0015-6","totalGasto":9000,"transacoes":2,"ticketMedio":4500,"percentual":7.87,"deputadosMesmoPartido":3,"alertaConcentracao":false,"alertaMesmoPartido":true},{"fornecedor":"MASTERGRAF","cnpjCpf":"103.364.180/0012-8","totalGasto":9000,"transacoes":2,"ticketMedio":4500,"percentual":7.87,"deputadosMesmoPartido":2,"alertaConcentracao":false,"alertaMesmoPartido":true},{"fornecedor":"REDEE - AGENCIA DIGITAL","cnpjCpf":"496.299.220/0015-1","totalGasto":9000,"transacoes":2,"ticketMedio":4500,"percentual":7.87,"deputadosMesmoPartido":3,"alertaConcentracao":false,"alertaMesmoPartido":true},{"fornecedor":"TERA EMPREENDIMENTOS CRIATIVOS","cnpjCpf":"141.147.980/0010-7","totalGasto":9000,"transacoes":2,"ticketMedio":4500,"percentual":7.87,"deputadosMesmoPartido":3,"alertaConcentracao":false,"alertaMesmoPartido":true}]},"categoriasDespesa":{"deputadoId":226553,"totalGasto":114344.94,"totalCategorias":6,"categorias":[{"categoria":"DIVULGAÇÃO DA ATIVIDADE PARLAMENTAR.","totalGasto":74720,"quantidadeDespesas":14,"percentual":65.35},{"categoria":"MANUTENÇÃO DE ESCRITÓRIO DE APOIO À ATIVIDADE PARLAMENTAR","totalGasto":12857.33,"quantidadeDespesas":5,"percentual":11.24},{"categoria":"LOCAÇÃO OU FRETAMENTO DE VEÍCULOS AUTOMOTORES","totalGasto":10881,"quantidadeDespesas":3,"percentual":9.52},{"categoria":"PASSAGEM AÉREA - SIGEPA","totalGasto":9609.13,"quantidadeDespesas":11,"percentual":8.4},{"categoria":"COMBUSTÍVEIS E LUBRIFICANTES.","totalGasto":6272.07,"quantidadeDespesas":24,"percentual":5.49},{"categoria":"TELEFONIA","totalGasto":5.41,"quantidadeDespesas":4,"percentual":0}]}}
